{
    "data":[
        {
            "name": "company1",
            "description": "hellooo",
            "industryType": "Software",
            "isActive": true,
            "address": "st. 1",
            "country": "Egypt",
            "city": "Cairo"
        },
        {
            "name": "company2",
            "description": "hellooo",
            "industryType": "Software",
            "isActive": true,
            "address": "st. 1",
            "country": "Egypt",
            "city": "Cairo"
        },
        {
            "name": "company3",
            "description": "hellooo",
            "industryType": "Sales",
            "isActive": false,
            "address": "st. 1",
            "country": "Egypt",
            "city": "Cairo"
        },
        {
            "name": "company4",
            "description": "hellooo",
            "industryType": "Sales",
            "isActive": true,
            "address": "st. 1",
            "country": "Germany",
            "city": "Berlin"
        },
        {
            "name": "company5",
            "description": "hellooo hi how are you",
            "industryType": "Development",
            "isActive": true,
            "address": "st. 1",
            "country": "France",
            "city": "Paris"
        }
    ]
}